yaqd_edaq/VERSION
yaqd_edaq/__init__.py
yaqd_edaq/__version__.py
yaqd_edaq/_edaq_isopod.py
yaqd_edaq/edaq-isopod.avpr
yaqd_edaq/edaq-isopod.toml
yaqd_edaq-2021.10.0.dist-info/entry_points.txt
yaqd_edaq-2021.10.0.dist-info/LICENSE
yaqd_edaq-2021.10.0.dist-info/WHEEL
yaqd_edaq-2021.10.0.dist-info/METADATA
yaqd_edaq-2021.10.0.dist-info/RECORD
