Metadata-Version: 2.1
Name: yaqd-edaq
Version: 2021.10.0
Summary: yaq daemons for edaq sensor recording systems
Home-page: https://yaq.fyi
Author: Blaise Thompson
Author-email: blaise@untzag.com
Requires-Python: >=3.7
Classifier: Development Status :: 2 - Pre-Alpha
Classifier: Intended Audience :: Science/Research
Classifier: License :: OSI Approved :: GNU Lesser General Public License v3 (LGPLv3)
Classifier: Natural Language :: English
Classifier: Programming Language :: Python :: 3
Classifier: Programming Language :: Python :: 3.7
Classifier: Programming Language :: Python :: 3.8
Classifier: Topic :: Scientific/Engineering
Requires-Dist: yaqd-core>=2020.06.3
Requires-Dist: pyserial
Requires-Dist: black ; extra == "dev"
Requires-Dist: pre-commit ; extra == "dev"
Project-URL: Issues, https://gitlab.com/yaq/yaqd-edaq/issues
Project-URL: Source, https://gitlab.com/yaq/yaqd-edaq
Provides-Extra: dev
